context_portal_mcp/main.py
context_portal_mcp/core/config.py
context_portal_mcp/core/embedding_service.py
context_portal_mcp/core/exceptions.py
context_portal_mcp/core/workspace_detector.py
context_portal_mcp/db/database.py
context_portal_mcp/db/models.py
context_portal_mcp/db/vector_store_service.py
context_portal_mcp/handlers/mcp_handlers.py
context_portal_mcp-0.3.13.dist-info/licenses/LICENSE
context_portal_mcp-0.3.13.dist-info/METADATA
context_portal_mcp-0.3.13.dist-info/WHEEL
context_portal_mcp-0.3.13.dist-info/entry_points.txt
context_portal_mcp-0.3.13.dist-info/top_level.txt
context_portal_mcp-0.3.13.dist-info/RECORD
