Metadata-Version: 2.4
Name: context-portal-mcp
Version: 0.3.13
Summary: A Model Context Protocol (MCP) server for managing structured project context.
Author-email: Scott McLeod <contextportal@gmail.com>
License: Apache-2.0
Project-URL: Homepage, https://github.com/GreatScottyMac/context-portal
Project-URL: Bug Reports, https://github.com/GreatScottyMac/context-portal/issues
Project-URL: Source, https://github.com/GreatScottyMac/context-portal
Project-URL: Documentation, https://github.com/GreatScottyMac/context-portal
Keywords: mcp,context,portal,fastapi,server
Classifier: Programming Language :: Python :: 3
Classifier: Programming Language :: Python :: 3.10
Classifier: Programming Language :: Python :: 3.11
Classifier: Programming Language :: Python :: 3.12
Classifier: Programming Language :: Python :: 3.13
Classifier: License :: OSI Approved :: Apache Software License
Classifier: Operating System :: OS Independent
Classifier: Development Status :: 4 - Beta
Classifier: Intended Audience :: Developers
Classifier: Topic :: Software Development :: Libraries :: Python Modules
Requires-Python: >=3.10
License-File: LICENSE
Requires-Dist: fastapi>=0.120.0
Requires-Dist: uvicorn[standard]>=0.38.0
Requires-Dist: pydantic>=2.12.5
Requires-Dist: fastmcp>=2.13.3
Requires-Dist: mcp>=1.23.0
Requires-Dist: sentence-transformers>=3.3.1
Requires-Dist: chromadb>=1.3.5
Requires-Dist: alembic>=1.17.2
Requires-Dist: authlib>=1.6.5
Requires-Dist: urllib3>=2.6.0
Requires-Dist: filelock>=3.16.2
Provides-Extra: dev
Requires-Dist: pytest>=7.0.0; extra == "dev"
Requires-Dist: pytest-asyncio; extra == "dev"
Requires-Dist: black; extra == "dev"
Requires-Dist: isort; extra == "dev"
Requires-Dist: flake8; extra == "dev"
Requires-Dist: mypy; extra == "dev"
Provides-Extra: test
Requires-Dist: pytest>=7.0.0; extra == "test"
Requires-Dist: pytest-asyncio; extra == "test"
Requires-Dist: pytest-cov; extra == "test"
Dynamic: license-file
